mupy/__init__.py
mupy/main.py
mupy/mupy.py
mupy/mutation/__init__.py
mupy/mutation/operators_finders.py
mupy/mutation/finders/__init__.py
mupy/mutation/finders/arith_op_finders.py
mupy/mutation/finders/bool_op_finders.py
mupy/mutation/finders/comp_op_finders.py
mupy/mutation/finders/const_finders.py
mupy/mutation/mutators/__init__.py
mupy/mutation/mutators/arith_op_mutator.py
mupy/mutation/mutators/bool_op_mutator.py
mupy/mutation/mutators/comp_op_mutator.py
mupy/mutation/mutators/const_mutator.py
mupy/server/__init__.py
mupy/server/server.py
mupy/server/static/favicon.ico
mupy/server/static/index.html
mupy/server/static/python-logo.svg
mupy/server/static/assets/__init__.py
mupy/server/static/assets/abap-TJ9JPO_o.js
mupy/server/static/assets/apex-fsuB5XsU.js
mupy/server/static/assets/azcli-5Up7nT0C.js
mupy/server/static/assets/bat-3yt5BTLC.js
mupy/server/static/assets/bicep-fwpFf1QR.js
mupy/server/static/assets/cameligo-cirCWOMO.js
mupy/server/static/assets/clojure-pRsr-ni6.js
mupy/server/static/assets/codicon-B7HMvkfX.ttf
mupy/server/static/assets/coffee-v6Xl4flH.js
mupy/server/static/assets/cpp-TR_j0MGC.js
mupy/server/static/assets/csharp-8jM-JXx5.js
mupy/server/static/assets/csp-3I2AinGx.js
mupy/server/static/assets/css-MHM-5ikl.js
mupy/server/static/assets/css.worker-_3MqMzan.js
mupy/server/static/assets/cssMode-5xMOQWgc.js
mupy/server/static/assets/cypher-VSDHz4vU.js
mupy/server/static/assets/dart-HfP09AJd.js
mupy/server/static/assets/dockerfile-Ii5-xKAy.js
mupy/server/static/assets/ecl-SqIXq25X.js
mupy/server/static/assets/editor.worker-weymZOpQ.js
mupy/server/static/assets/elixir-AprjDB11.js
mupy/server/static/assets/flow9-dknFQu1u.js
mupy/server/static/assets/freemarker2-luoodEux.js
mupy/server/static/assets/fsharp-ZcRcioj2.js
mupy/server/static/assets/go-CCHKUeY6.js
mupy/server/static/assets/graphql-jfm_tSg4.js
mupy/server/static/assets/handlebars-0CA6L17_.js
mupy/server/static/assets/hcl-dm7hMJK8.js
mupy/server/static/assets/html-XBxWfggt.js
mupy_hiro-0.0.15.dist-info/METADATA
mupy_hiro-0.0.15.dist-info/WHEEL
mupy_hiro-0.0.15.dist-info/top_level.txt
mupy_hiro-0.0.15.dist-info/RECORD
